LICENSE
MANIFEST.in
README.md
setup.cfg
setup.py
jupyter_themer.egg-info/PKG-INFO
jupyter_themer.egg-info/SOURCES.txt
jupyter_themer.egg-info/dependency_links.txt
jupyter_themer.egg-info/entry_points.txt
jupyter_themer.egg-info/requires.txt
jupyter_themer.egg-info/top_level.txt
jupythemer/__init__.py
jupythemer/jupythemer.py
jupythemer/styles/background/dark.css
jupythemer/styles/code_font/Inconsolata.css
jupythemer/styles/code_font/Source_Code_Pro.css
jupythemer/styles/code_font/Ubuntu_Mono.css
jupythemer/styles/color/3024-day.css
jupythemer/styles/color/3024-night.css
jupythemer/styles/color/abcdef.css
jupythemer/styles/color/ambiance.css
jupythemer/styles/color/base16-dark.css
jupythemer/styles/color/base16-light.css
jupythemer/styles/color/blackboard.css
jupythemer/styles/color/cobalt.css
jupythemer/styles/color/colorforth.css
jupythemer/styles/color/dracula.css
jupythemer/styles/color/eclipse.css
jupythemer/styles/color/elegant.css
jupythemer/styles/color/erlang-dark.css
jupythemer/styles/color/icecoder.css
jupythemer/styles/color/lesser-dark.css
jupythemer/styles/color/liquibyte.css
jupythemer/styles/color/material.css
jupythemer/styles/color/mbo.css
jupythemer/styles/color/mdn-like.css
jupythemer/styles/color/midnight.css
jupythemer/styles/color/monokai.css
jupythemer/styles/color/neat.css
jupythemer/styles/color/neo.css
jupythemer/styles/color/night.css
jupythemer/styles/color/paraiso-dark.css
jupythemer/styles/color/paraiso-light.css
jupythemer/styles/color/pastel-on-dark.css
jupythemer/styles/color/rubyblue.css
jupythemer/styles/color/seti.css
jupythemer/styles/color/solarized-dark.css
jupythemer/styles/color/solarized-light.css
jupythemer/styles/color/the-matrix.css
jupythemer/styles/color/tomorrow-night-bright.css
jupythemer/styles/color/tomorrow-night-eighties.css
jupythemer/styles/color/ttcn.css
jupythemer/styles/color/twilight.css
jupythemer/styles/color/vibrant-ink.css
jupythemer/styles/color/xq-dark.css
jupythemer/styles/color/xq-light.css
jupythemer/styles/color/yeti.css
jupythemer/styles/color/zenburn.css
jupythemer/styles/layout/hovertable.css
jupythemer/styles/layout/wide.css
jupythemer/styles/typography/serif.css