Metadata-Version: 1.0
Name: jupyter-themer
Version: 0.4.0
Summary: Custom CSS themer for jupyter notebooks
Home-page: https://github.com/transcranial/jupyter-themer
Author: Leon Chen
Author-email: lchen3@gmail.com
License: MIT
Keywords: jupyter,ipython,notebook,themes,css
Platform: UNKNOWN
